{
  "canisters": {
    "asset_storage": {
      "candid": "wasm/assetstorage.did",
      "init_arg": "opt variant { Init = record {} }",
      "package": "asset_storage",
      "type": "custom",
      "wasm": "wasm/assetstorage.wasm.gz"
    },
    "icrc7_launchpad": {
      "candid": "src/icrc7_launchpad/icrc7_launchpad.did",
      "package": "icrc7_launchpad",
      "type": "rust"
    },
    "icrc7": {
      "candid": "src/icrc7/icrc7.did",
      "package": "icrc7",
      "type": "rust"
    },
    "icrc7_archive": {
      "candid": "src/icrc7_archive/icrc7_archive.did",
      "package": "icrc7_archive",
      "type": "rust"
    }
  },
  "defaults": {
    "build": {
      "args": "",
      "packtool": ""
    }
  },
  "output_env_file": ".env",
  "version": 1
}
